pyxivapi/__init__.py
pyxivapi/client.py
pyxivapi/decorators.py
pyxivapi/exceptions.py
pyxivapi/models.py
pyxivapi-0.5.1.dist-info/LICENSE
pyxivapi-0.5.1.dist-info/METADATA
pyxivapi-0.5.1.dist-info/WHEEL
pyxivapi-0.5.1.dist-info/top_level.txt
pyxivapi-0.5.1.dist-info/RECORD
