Metadata-Version: 2.1
Name: pyxivapi
Version: 0.5.1
Summary: An asynchronous Python client for XIVAPI
Home-page: https://github.com/xivapi/xivapi-py
Author: Lethys
Author-email: seraymericbot@gmail.com
License: MIT
Keywords: ffxiv xivapi
Platform: UNKNOWN
Classifier: License :: OSI Approved :: MIT License
Classifier: Intended Audience :: Developers
Classifier: Natural Language :: English
Classifier: Operating System :: OS Independent
Classifier: Programming Language :: Python :: 3.7
Classifier: Programming Language :: Python :: 3.8
Classifier: Topic :: Internet
Classifier: Topic :: Software Development :: Libraries
Classifier: Topic :: Software Development :: Libraries :: Python Modules
Classifier: Topic :: Utilities
